aio_tinder-0.1.8.dist-info/DESCRIPTION.rst
aio_tinder-0.1.8.dist-info/METADATA
aio_tinder-0.1.8.dist-info/RECORD
aio_tinder-0.1.8.dist-info/WHEEL
aio_tinder-0.1.8.dist-info/metadata.json
aio_tinder-0.1.8.dist-info/top_level.txt
aiotinder/__init__.py
aiotinder/settings.py
aiotinder/controllers/__init__.py
aiotinder/controllers/api.py
aiotinder/controllers/exceptions.py
aiotinder/controllers/tinder.py
aiotinder/models/__init__.py
aiotinder/models/model.py
